setup.py
eveliver/__init__.py
eveliver/clean.py
eveliver/conversion.py
eveliver/json.py
eveliver/logger.py
eveliver/padding.py
eveliver/span.py
eveliver/timer.py
eveliver/trainer.py
eveliver/visualization.py
eveliver.egg-info/PKG-INFO
eveliver.egg-info/SOURCES.txt
eveliver.egg-info/dependency_links.txt
eveliver.egg-info/requires.txt
eveliver.egg-info/top_level.txt