Metadata-Version: 1.0
Name: eveliver
Version: 1.14.0
Summary: Some pytorch utilities for NLP
Home-page: https://github.com/jiajudu/eveliver
Author: Jiaju Du
Author-email: i@dujiaju.me
License: UNKNOWN
Platform: UNKNOWN
